hellobiswatest/__init__.py
hellobiswatest-0.1.88.dist-info/WHEEL
hellobiswatest-0.1.88.dist-info/METADATA
hellobiswatest-0.1.88.dist-info/RECORD
